adafruit_hid/__init__.py
adafruit_hid/consumer_control.py
adafruit_hid/consumer_control_code.py
adafruit_hid/digitizer.py
adafruit_hid/gamepad.py
adafruit_hid/keyboard.py
adafruit_hid/keyboard_layout_base.py
adafruit_hid/keyboard_layout_us.py
adafruit_hid/keycode.py
adafruit_hid/mouse.py
quax_circuitpython_hid-6.1.5.dist-info/licenses/LICENSE
quax_circuitpython_hid-6.1.5.dist-info/METADATA
quax_circuitpython_hid-6.1.5.dist-info/WHEEL
quax_circuitpython_hid-6.1.5.dist-info/top_level.txt
quax_circuitpython_hid-6.1.5.dist-info/RECORD
