Metadata-Version: 2.4
Name: quax-circuitpython-hid
Version: 6.1.5
Summary: CircuitPython helper library for simulating HID devices.
Author-email: quaxalber <pypi@quaxalber.de>, Adafruit Industries <circuitpython@adafruit.com>
License: MIT
Project-URL: Homepage, https://github.com/quaxalber/Adafruit_CircuitPython_HID
Keywords: adafruit,hid,human,interface,device,keyboard,mouse,keycode,keypadhardware,micropython,circuitpython
Classifier: Intended Audience :: Developers
Classifier: Topic :: Software Development :: Libraries
Classifier: Topic :: Software Development :: Embedded Systems
Classifier: Topic :: System :: Hardware
Classifier: License :: OSI Approved :: MIT License
Classifier: Programming Language :: Python :: 3
License-File: LICENSE
Requires-Dist: quax-Blinka
Provides-Extra: optional
Dynamic: license-file
